setup.cfg
setup.py
django_modeladmin_utils.egg-info/PKG-INFO
django_modeladmin_utils.egg-info/SOURCES.txt
django_modeladmin_utils.egg-info/dependency_links.txt
django_modeladmin_utils.egg-info/requires.txt
django_modeladmin_utils.egg-info/top_level.txt
modeladmin_utils/__init__.py
modeladmin_utils/mixins/__init__.py
modeladmin_utils/mixins/limited_inlines.py
modeladmin_utils/mixins/location.py
modeladmin_utils/mixins/search.py
modeladmin_utils/templatetags/__init__.py
modeladmin_utils/templatetags/modeladmin_links.py