Metadata-Version: 1.0
Name: django-modeladmin-utils
Version: 1.0.0
Summary: ModelAdmin utils
Home-page: https://github.com/modlinltd/ModelAdmin-Utils
Author: Pavel Savchenko
Author-email: pavel@modlinltd.com
License: MIT
Platform: UNKNOWN
Classifier: Development Status :: 5 - Production/Stable
Classifier: Environment :: Web Environment
Classifier: Framework :: Django
Classifier: Framework :: Django :: 1.4
Classifier: Framework :: Django :: 1.5
Classifier: Framework :: Django :: 1.6
Classifier: Framework :: Django :: 1.7
Classifier: Intended Audience :: Developers
Classifier: Programming Language :: Python
Classifier: License :: OSI Approved :: MIT License
Classifier: Programming Language :: Python :: 2.7
